daedalus/__init__.py
daedalus/__main__.py
daedalus/daedalus.py
daedalus/styles.py
daedalus/validators.py
daedalus/5G/SDR/bladerf.yml
daedalus/5G/SDR/ettus-gnb.yml
daedalus/5G/SDR/ettus.yml
daedalus/5G/SIMULATED/srsran-enb.yml
daedalus/5G/SIMULATED/srsran-gnb.yml
daedalus/5G/SIMULATED/srsran-gue.yml
daedalus/5G/SIMULATED/srsran-ue.yml
daedalus/5G/SIMULATED/ueransim-gnb.yml
daedalus/5G/SIMULATED/ueransim-ue.yml
daedalus/5G/UERANSIM/scripts/add_default_route.sh
daedalus/5G/UERANSIM/scripts/run_rfn_gnb.sh
daedalus/5G/UERANSIM/scripts/run_ue.sh
daedalus/5G/configs/imsis.json
daedalus/5G/configs/slice.yaml
daedalus/5G/configs/UERANSIM/gnb.yaml
daedalus/5G/configs/UERANSIM/ue.yaml
daedalus/5G/configs/faucet/acls.yaml
daedalus/5G/configs/faucet/faucet.yaml
daedalus/5G/configs/open5gs/smf.yaml
daedalus/5G/configs/srsRAN/blade-rr.conf
daedalus/5G/configs/srsRAN/enb.conf
daedalus/5G/configs/srsRAN/ettus-nrr.conf
daedalus/5G/configs/srsRAN/ettus-rr.conf
daedalus/5G/configs/srsRAN/rb.conf
daedalus/5G/configs/srsRAN/rr.conf
daedalus/5G/configs/srsRAN/sib.conf
daedalus/5G/configs/srsRAN/ue.conf
daedalus/5G/configs/srsRAN/virtual-nrr.conf
daedalus/5G/configs/srsRAN/virtual-rr.conf
daedalus/5G/core/core.yml
daedalus/5G/core/db.yml
daedalus/5G/core/epc.yml
daedalus/5G/core/ui.yml
daedalus/5G/core/upn.yml
daedalus/5G/open5gs/scripts/mmehc.sh
daedalus/5G/open5gs/scripts/nrfhc.sh
daedalus/5G/open5gs/scripts/run_db.sh
daedalus/5G/open5gs/scripts/run_smf.sh
daedalus/5G/open5gs/scripts/run_upf.sh
daedalus/5G/srsRAN/scripts/add_default_route.sh
daedalus/5G/srsRAN/scripts/run_rfn_enb.sh
daedalus/5G/srsRAN/scripts/start_srsue.sh
daedalus_5g-0.11.7.dist-info/METADATA
daedalus_5g-0.11.7.dist-info/WHEEL
daedalus_5g-0.11.7.dist-info/entry_points.txt
daedalus_5g-0.11.7.dist-info/top_level.txt
daedalus_5g-0.11.7.dist-info/RECORD
