Metadata-Version: 2.1
Name: daedalus-5g
Version: 0.11.7
Summary: A tool for creating 4G/5G environments both with SDRs and virtual simulation to run experiments in
Author-email: cglewis <clewis@iqt.org>
Classifier: Development Status :: 2 - Pre-Alpha
Classifier: License :: OSI Approved :: Apache Software License
Classifier: Programming Language :: Python
Requires-Python: >=3.8
Requires-Dist: docker ==6.1.3
Requires-Dist: dovesnap ==1.1.16
Requires-Dist: plumbum ==1.8.2
Requires-Dist: inquirer ==3.1.3
Provides-Extra: confuser
Requires-Dist: fusepy ; extra == 'confuser'
Provides-Extra: generate_fs
Requires-Dist: essential-generators ; extra == 'generate_fs'
Requires-Dist: numpy ; extra == 'generate_fs'
Provides-Extra: test
Requires-Dist: attrs ==23.1.0 ; extra == 'test'
Requires-Dist: codecov ==2.1.13 ; extra == 'test'
Requires-Dist: pylint ==3.0.1 ; extra == 'test'
Requires-Dist: pytype ==2023.10.5 ; extra == 'test'
Requires-Dist: pytest ==7.4.2 ; extra == 'test'
Requires-Dist: pytest-cov ==4.1.0 ; extra == 'test'
Requires-Dist: ruamel.yaml ~=0.17 ; extra == 'test'
